[{"description":"Экскурсия на суперкомпьютер","url":"https://www.hse.ru/ba/se/news/228085375.html","date_day":"19:ноя:2018"},{"description":"НИУ ВШЭ открывает конкурс научно-исследовательских работ для студентов всех вузов по всем направлениям","url":"https://sdo.hse.ru/leadership/announcements/222754246.html","date_day":"18:сен:2018"},{"description":"Бакалаврская программа «Программная инженерия» получила престижную международную аккредитацию","url":"/news/edu/222801427.html","date_day":"31:авг:2018"},{"description":"Сотрудников учебных офисов наградили благодарностями","url":"https://www.hse.ru/ba/se/news/222794542.html","date_day":"30:авг:2018"},{"description":"Поздравляем!","url":"https://www.hse.ru/ba/se/news/222351989.html","date_day":"12:авг:2018"},{"description":"Нетипичный программист: как посмотреть мир, разрабатывая мобильные приложения","url":"/news/admission/222011815.html","date_day":"1:авг:2018"},{"description":"V Международная конференция по анализу изображений, социальных сетей и текстов (АИСТ)","url":"https://pais.hse.ru/news/221517087.html","date_day":"17:июл:2018"},{"description":"23 студента \"Программной инженерии\" получили право перейти с коммерции на бюджет","url":"https://cs.hse.ru/news/221510671.html","date_day":"17:июл:2018"},{"description":"Выпускники рассказывают: Мария Горденко","url":"https://cs.hse.ru/news/220748829.html","date_day":"22:июн:2018"},{"description":"Поздравляем бакалавров Программной инженерии с успешной защитой выпускных работ!","url":"https://www.hse.ru/ba/se/news/220441519.html","date_day":"19:июн:2018"}]